{
  "version": "5.5.0",
  "flags": {},
  "shapes": [
    {
      "label": "P1-1_28너9283",
      "points": [
        [
          814.374755859375,
          491.97906494140625
        ],
        [
          1139.5751953125,
          490.3787536621094
        ],
        [
          1142.585205078125,
          565.5989379882812
        ],
        [
          817.6063842773438,
          561.8109741210938
        ]
      ],
      "group_id": null,
      "description": "",
      "shape_type": "polygon",
      "flags": {},
      "mask": null
    },
    {
      "label": "P1-1_28너9283",
      "points": [
        [
          814.374755859375,
          490.3787536621094
        ],
        [
          1142.585205078125,
          565.5989379882812
        ]
      ],
      "group_id": null,
      "description": "",
      "shape_type": "rectangle",
      "flags": {},
      "mask": null
    }
  ],
  "imagePath": "in_L01_0_20161126_073342_073343_462_28너9283.jpg",
  "imageData": null,
  "imageHeight": 1200,
  "imageWidth": 1600
}